spiffy/__init__.py
spiffy/__main__.py
spiffy/meshplotter.py
spiffy/meshplottercfg.txt
spiffy/orbit.py
spiffy/orbit2D.py
spiffy/orbit3D.py
spiffy/plotter.py
spiffy/satellite.py
spiffy-0.0.11.dist-info/LICENSE
spiffy-0.0.11.dist-info/METADATA
spiffy-0.0.11.dist-info/WHEEL
spiffy-0.0.11.dist-info/top_level.txt
spiffy-0.0.11.dist-info/RECORD
