Metadata-Version: 2.1
Name: spiffy
Version: 0.0.11
Summary: Space Interferometer Python Framework
Home-page: https://github.com/arthurpreis/spiffy
Author: Arthur Reis
Author-email: arpereis@gmail.com
License: UNKNOWN
Platform: UNKNOWN
Classifier: Development Status :: 2 - Pre-Alpha
Classifier: Programming Language :: Python :: 3
Classifier: License :: OSI Approved :: MIT License
Classifier: Operating System :: OS Independent
Classifier: Intended Audience :: Science/Research
Classifier: Topic :: Scientific/Engineering :: Astronomy
Classifier: Topic :: Scientific/Engineering :: Physics
Classifier: Topic :: Scientific/Engineering :: Visualization
Requires-Python: >=3.6
Requires-Dist: jupyterlab
Requires-Dist: matplotlib
Requires-Dist: notebook
Requires-Dist: numpy
Requires-Dist: PyQt5
Requires-Dist: sympy
Requires-Dist: vtk
Requires-Dist: mayavi
